importlab/__init__.py
importlab/environment.py
importlab/fs.py
importlab/graph.py
importlab/import_finder.py
importlab/output.py
importlab/parsepy.py
importlab/resolve.py
importlab/utils.py
importlab-0.8.1.data/scripts/importlab
importlab-0.8.1.dist-info/LICENSE
importlab-0.8.1.dist-info/METADATA
importlab-0.8.1.dist-info/WHEEL
importlab-0.8.1.dist-info/top_level.txt
importlab-0.8.1.dist-info/RECORD
