Metadata-Version: 2.1
Name: importlab
Version: 0.8.1
Summary: A library to calculate python dependency graphs.
Home-page: https://github.com/google/importlab
Maintainer: Google Inc.
Maintainer-email: pytype-dev@google.com
License: Apache 2.0
Classifier: Development Status :: 4 - Beta
Classifier: Intended Audience :: Developers
Classifier: License :: OSI Approved :: Apache Software License
Classifier: Programming Language :: Python
Classifier: Programming Language :: Python :: 3
Classifier: Programming Language :: Python :: Implementation :: CPython
Classifier: Topic :: Software Development
Requires-Python: >=3.6.0
License-File: LICENSE
